README.rst
setup.py
packsible/__init__.py
packsible/cli.py
packsible/images.py
packsible/server.py
packsible/utils.py
packsible.egg-info/PKG-INFO
packsible.egg-info/SOURCES.txt
packsible.egg-info/dependency_links.txt
packsible.egg-info/entry_points.txt
packsible.egg-info/not-zip-safe
packsible.egg-info/requires.txt
packsible.egg-info/top_level.txt