Metadata-Version: 1.0
Name: packsible
Version: 0.2.0
Summary: Combine the power of packer and ansible conveniently
Home-page: https://github.com/packsible/packsible
Author: Reuven V. Gonzales
Author-email: reuven@virtru.com
License: MIT
Platform: *nix
